{
	"$schema": "http://adaptivecards.io/schemas/adaptive-card.json",
	"type": "AdaptiveCard",
	"version": "1.0",
	"body": [
		{
			"type": "Input.Number",
			"id": "input1",
			"label": "Default Input.Number label"
		},
		{
			"type": "Input.Number",
			"id": "input2",
			"label": "Require Input.Number label",
			"isRequired": true,
			"errorMessage": "Required input"
		},
		{
			"type": "Input.Number",
			"id": "input3",
			"label": "Longer label to verify label wrapping for an Input.Number. If that was not long enough, then this should make it long enough. Did you know that slugs have four noses?"
		}
	],
	"actions": [
		{
			"type": "Action.Submit",
			"title": "Submit"
		}
	]
}
