<annotation>
	<folder>dataset_final</folder>
	<filename>71.png</filename>
	<path>/home/keerthanamanoharan/Documents/office_work/Pic2Code/dataset_final/71.png</path>
	<source>
		<database>Unknown</database>
	</source>
	<size>
		<width>567</width>
		<height>169</height>
		<depth>3</depth>
	</size>
	<segmented>0</segmented>
	<object>
		<name>checkbox</name>
		<pose>Unspecified</pose>
		<truncated>0</truncated>
		<difficult>0</difficult>
		<bndbox>
			<xmin>19</xmin>
			<ymin>63</ymin>
			<xmax>116</xmax>
			<ymax>91</ymax>
		</bndbox>
	</object>
	<object>
		<name>checkbox</name>
		<pose>Unspecified</pose>
		<truncated>0</truncated>
		<difficult>0</difficult>
		<bndbox>
			<xmin>123</xmin>
			<ymin>61</ymin>
			<xmax>219</xmax>
			<ymax>91</ymax>
		</bndbox>
	</object>
	<object>
		<name>checkbox</name>
		<pose>Unspecified</pose>
		<truncated>0</truncated>
		<difficult>0</difficult>
		<bndbox>
			<xmin>223</xmin>
			<ymin>61</ymin>
			<xmax>321</xmax>
			<ymax>92</ymax>
		</bndbox>
	</object>
	<object>
		<name>checkbox</name>
		<pose>Unspecified</pose>
		<truncated>0</truncated>
		<difficult>0</difficult>
		<bndbox>
			<xmin>324</xmin>
			<ymin>61</ymin>
			<xmax>429</xmax>
			<ymax>94</ymax>
		</bndbox>
	</object>
	<object>
		<name>textbox</name>
		<pose>Unspecified</pose>
		<truncated>0</truncated>
		<difficult>0</difficult>
		<bndbox>
			<xmin>168</xmin>
			<ymin>13</ymin>
			<xmax>397</xmax>
			<ymax>50</ymax>
		</bndbox>
	</object>
	<object>
		<name>textbox</name>
		<pose>Unspecified</pose>
		<truncated>0</truncated>
		<difficult>0</difficult>
		<bndbox>
			<xmin>21</xmin>
			<ymin>96</ymin>
			<xmax>546</xmax>
			<ymax>146</ymax>
		</bndbox>
	</object>
</annotation>
